immundata/__init__.py
immundata/core.py
immundata/data.py
immundata/grouped.py
immundata/models.py
immundata/py.typed
immundata/reader.py
immundata/source.py
immundata-0.1.0.dist-info/METADATA
immundata-0.1.0.dist-info/WHEEL
immundata-0.1.0.dist-info/top_level.txt
immundata-0.1.0.dist-info/RECORD
