Metadata-Version: 2.2
Name: immundata
Version: 0.1.0
Summary: A data layer for single-cell, spatial and bulk immunomics, providing a unified structure for immune receptor repertoire data.
Author-email: Vadim Nazarov <support@immunomind.com>
Requires-Python: >=3.11
Requires-Dist: airr>=1.5.1
Requires-Dist: polars>=1.25.2
